[
  {
    "ADa4WiFfL1gcdYfrRQw7SB": {
      "t": 0,
      "e": "Area3",
      "p": {
        "tt": "Personal",
        "ix": 10
      }
    }
  },
  {
    "Asq5hh5hVBFhHrcFZeeYYS": {
      "t": 0,
      "e": "Task6",
      "p": {
        "tt": "Read book",
        "st": 1,
        "ss": 0,
        "tp": 0,
        "ix": 10,
        "cd": 1735689600,
        "md": 1735689600,
        "ar": [
          "ADa4WiFfL1gcdYfrRQw7SB"
        ]
      }
    }
  },
  {
    "B12u2kzxrffnpBF1mw38uF": {
      "t": 0,
      "e": "Task6",
      "p": {
        "tt": "Write report",
        "st": 1,
        "ss": 0,
        "tp": 0,
        "ix": 10,
        "cd": 1735689600,
        "md": 1735689600
      }
    }
  }
]
